newg_dl/__init__.py
newg_dl/newgrounds_dl.py
newg_dl-0.2.9.dist-info/LICENSE
newg_dl-0.2.9.dist-info/METADATA
newg_dl-0.2.9.dist-info/WHEEL
newg_dl-0.2.9.dist-info/entry_points.txt
newg_dl-0.2.9.dist-info/RECORD
